many/__init__.py
many/default-config.ini
many/engine.py
many/migrate.py
many/revise.py
many/templates/__init__.py
many/templates/base.py.mako
many/templates/elasticsearch.py.mako
many/templates/spark.py.mako
many/templates/sqlalchemy.py.mako
many/utils.py
many_migrations-1.1.dist-info/LICENSE
many_migrations-1.1.dist-info/METADATA
many_migrations-1.1.dist-info/WHEEL
many_migrations-1.1.dist-info/RECORD
