Metadata-Version: 2.1
Name: many-migrations
Version: 1.1
Summary: 
Author: Thijsvandepoll
Author-email: thijsvandepoll@gmail.com
Requires-Python: >=3.9,<4.0
Classifier: Programming Language :: Python :: 3
Classifier: Programming Language :: Python :: 3.9
Classifier: Programming Language :: Python :: 3.10
Classifier: Programming Language :: Python :: 3.11
Requires-Dist: mako (>=1.3.10,<2.0.0)
Requires-Dist: typer (>=0.19.1,<0.20.0)
